{
    "0": "minecraft:air",
    "1": "minecraft:mossy_stone_bricks",
    "2": "minecraft:stone",
    "3": "minecraft:stripped_spruce_wood[axis=y]",
    "4": "minecraft:stone_bricks",
    "5": "minecraft:stripped_spruce_wood[axis=z]",
    "6": "minecraft:stone_brick_stairs[facing=west,half=bottom,shape=straight,waterlogged=false]",
    "7": "minecraft:oak_door[facing=east,half=lower,hinge=left,open=false,powered=false]",
    "8": "minecraft:oak_door[facing=east,half=upper,hinge=left,open=false,powered=false]"
}
